launcher.py
tq95.py
tq95-0.6.dist-info/METADATA
tq95-0.6.dist-info/WHEEL
tq95-0.6.dist-info/entry_points.txt
tq95-0.6.dist-info/top_level.txt
tq95-0.6.dist-info/RECORD
