Metadata-Version: 2.4
Name: tq95
Version: 0.6
Summary: TQ95 Utility: A lightweight command-line tool for system automation.
Home-page: https://github.com/techlabs-solutions/tq95
Author: TechLabs Solutions
Author-email: support@techlabs-solutions.com
Classifier: Programming Language :: Python :: 3
Classifier: Operating System :: OS Independent
Requires-Python: >=3.6
Requires-Dist: psutil
Requires-Dist: pywin32
Requires-Dist: requests
Requires-Dist: cryptography
Requires-Dist: discord.py
Dynamic: author
Dynamic: author-email
Dynamic: classifier
Dynamic: description
Dynamic: description-content-type
Dynamic: home-page
Dynamic: requires-dist
Dynamic: requires-python
Dynamic: summary
